commcare_export/VERSION
commcare_export/__init__.py
commcare_export/builtin_queries.py
commcare_export/checkpoint.py
commcare_export/cli.py
commcare_export/commcare_hq_client.py
commcare_export/commcare_minilinq.py
commcare_export/data_types.py
commcare_export/env.py
commcare_export/excel_query.py
commcare_export/exceptions.py
commcare_export/jsonpath_utils.py
commcare_export/location_info_provider.py
commcare_export/map_format.py
commcare_export/minilinq.py
commcare_export/misc.py
commcare_export/repeatable_iterator.py
commcare_export/specs.py
commcare_export/utils.py
commcare_export/utils_cli.py
commcare_export/version.py
commcare_export/writers.py
commcare_export-1.14.0.dist-info/METADATA
commcare_export-1.14.0.dist-info/WHEEL
commcare_export-1.14.0.dist-info/entry_points.txt
commcare_export-1.14.0.dist-info/top_level.txt
commcare_export-1.14.0.dist-info/RECORD
