Metadata-Version: 2.4
Name: commcare-export
Version: 1.14.0
Summary: A command-line tool (and Python library) to extract data from CommCare HQ into a SQL database or Excel workbook
Author-email: Dimagi <information@dimagi.com>
License: MIT
Project-URL: Homepage, https://github.com/dimagi/commcare-export
Classifier: Development Status :: 4 - Beta
Classifier: Environment :: Console
Classifier: Intended Audience :: Developers
Classifier: Intended Audience :: Healthcare Industry
Classifier: Intended Audience :: Science/Research
Classifier: Intended Audience :: System Administrators
Classifier: Intended Audience :: End Users/Desktop
Classifier: License :: OSI Approved :: MIT License
Classifier: Programming Language :: Python :: 3
Classifier: Programming Language :: Python :: 3.9
Classifier: Programming Language :: Python :: 3.10
Classifier: Programming Language :: Python :: 3.11
Classifier: Programming Language :: Python :: 3.12
Classifier: Programming Language :: Python :: 3.13
Classifier: Topic :: Database
Classifier: Topic :: Software Development :: Interpreters
Classifier: Topic :: System :: Archiving
Classifier: Topic :: System :: Distributed Computing
Requires-Python: >=3.9
Requires-Dist: alembic
Requires-Dist: backoff>=2.0
Requires-Dist: jsonpath-ng~=1.6.0
Requires-Dist: ndg-httpsclient
Requires-Dist: openpyxl==3.1.5
Requires-Dist: python-dateutil
Requires-Dist: pytz
Requires-Dist: requests
Requires-Dist: simplejson
Requires-Dist: sqlalchemy~=1.4
Requires-Dist: sqlalchemy-migrate
Provides-Extra: test
Requires-Dist: pytest; extra == "test"
Requires-Dist: psycopg2-binary; extra == "test"
Requires-Dist: mock; extra == "test"
Provides-Extra: base-sql
Requires-Dist: SQLAlchemy; extra == "base-sql"
Requires-Dist: alembic; extra == "base-sql"
Provides-Extra: postgres
Requires-Dist: SQLAlchemy; extra == "postgres"
Requires-Dist: alembic; extra == "postgres"
Requires-Dist: psycopg2-binary; extra == "postgres"
Provides-Extra: mysql
Requires-Dist: SQLAlchemy; extra == "mysql"
Requires-Dist: alembic; extra == "mysql"
Requires-Dist: pymysql; extra == "mysql"
Provides-Extra: odbc
Requires-Dist: SQLAlchemy; extra == "odbc"
Requires-Dist: alembic; extra == "odbc"
Requires-Dist: pyodbc; extra == "odbc"
Provides-Extra: xlsx
Requires-Dist: openpyxl; extra == "xlsx"
Provides-Extra: xls
Requires-Dist: xlwt; extra == "xls"
Provides-Extra: executable
Requires-Dist: chardet; extra == "executable"
Requires-Dist: psycopg2-binary; extra == "executable"
Requires-Dist: pymysql; extra == "executable"
Requires-Dist: pyodbc; extra == "executable"
Requires-Dist: xlwt; extra == "executable"
Requires-Dist: openpyxl; extra == "executable"
